{"2019-10":[{"title":"Java/java网络爬虫","date":"2019-10-13T11:48:01.892Z","link":"/2019/10/13/Java/java网络爬虫/"}],"2019-11":[{"title":"Java/3天精通Java网络爬虫","date":"2019-11-06T07:29:25.902Z","link":"/2019/11/06/Java/3天精通Java网络爬虫/"},{"title":"Web/Basic/canvas","date":"2019-11-20T08:41:45.647Z","link":"/2019/11/20/Web/Basic/canvas/"},{"title":"Java/Java集合超详细简单文档","date":"2019-11-20T08:42:13.699Z","link":"/2019/11/20/Java/Java集合超详细简单文档/"},{"title":"Web/Basic/html问题","date":"2019-11-29T03:27:26.970Z","link":"/2019/11/29/Web/Basic/html问题/"}],"2019-12":[{"title":"CDN","date":"2019-12-30T02:38:26.097Z","link":"/2019/12/30/CDN/"}],"2020-1":[{"title":"计算机基础/电脑硬件/电脑硬件","date":"2020-01-03T03:13:18.728Z","link":"/2020/01/03/计算机基础/电脑硬件/电脑硬件/"}],"2020-2":[{"title":"Java/Java网络爬虫/3天精通Java网络爬虫","date":"2020-02-12T04:42:32.067Z","link":"/2020/02/12/Java/Java网络爬虫/3天精通Java网络爬虫/"},{"title":"Web/Basic/HMTL/HTML5","date":"2020-02-12T04:42:32.074Z","link":"/2020/02/12/Web/Basic/HMTL/HTML5/"},{"title":"Java/Java网络爬虫/java网络爬虫","date":"2020-02-12T04:42:32.079Z","link":"/2020/02/12/Java/Java网络爬虫/java网络爬虫/"},{"title":"Java/Java Basic/Java集合超详细简单文档","date":"2020-02-12T04:42:32.083Z","link":"/2020/02/12/Java/Java Basic/Java集合超详细简单文档/"},{"title":"静态blog/Markdown/Markdown语法","date":"2020-02-14T16:10:25.892Z","link":"/2020/02/15/静态blog/Markdown/Markdown语法/"},{"title":"Web/Basic/id","date":"2020-02-15T11:43:18.025Z","link":"/2020/02/15/Web/Basic/id/"},{"title":"计算机基础/硬件","date":"2020-02-15T12:20:17.334Z","link":"/2020/02/15/计算机基础/硬件/"},{"title":"计算机基础/黑苹果教程","date":"2020-02-15T12:25:14.732Z","link":"/2020/02/15/计算机基础/黑苹果教程/"},{"title":"Web/JavaScript/JQuery/JQuery","date":"2020-02-16T09:08:03.988Z","link":"/2020/02/16/Web/JavaScript/JQuery/JQuery/"},{"title":"计算机基础/操作系统","date":"2020-02-19T05:14:07.069Z","link":"/2020/02/19/计算机基础/操作系统/"},{"title":"软件/win10电脑技巧","date":"2020-02-19T06:50:27.013Z","link":"/2020/02/19/软件/win10电脑技巧/"},{"title":"Python学习","date":"2020-02-22T11:23:07.564Z","link":"/2020/02/22/python/Python学习/"},{"title":"计算机基础/计算机组装与维护","date":"2020-02-23T14:11:30.343Z","link":"/2020/02/23/计算机基础/计算机组装与维护/"},{"title":"Python爬虫","date":"2020-02-26T07:44:28.352Z","link":"/2020/02/26/python/python爬虫/"},{"title":"Web/WeChatApplet/微信小程序","date":"2020-02-27T09:48:35.171Z","link":"/2020/02/27/Web/WeChatApplet/微信小程序/"},{"title":"Web/Frame/React/React","date":"2020-02-28T10:11:37.013Z","link":"/2020/02/28/Web/Frame/React/React/"}],"2020-3":[{"title":"Web/Frame/Node.js/nodejs视频","date":"2020-03-05T09:13:48.415Z","link":"/2020/03/05/Web/Frame/Node.js/nodejs视频/"},{"title":"Web/JavaScript/ES6/ES6","date":"2020-03-06T08:11:25.211Z","link":"/2020/03/06/Web/JavaScript/ES6/ES6/"},{"title":"计算机基础/V2RAY+WS+TLS安装","date":"2020-03-13T00:54:24.928Z","link":"/2020/03/13/计算机基础/V2RAY+WS+TLS安装/"},{"title":"Git教程","date":"2020-03-13T02:16:42.878Z","link":"/2020/03/13/Git/Git教程/"},{"title":"Git的常用命令","date":"2020-03-13T08:48:42.115Z","link":"/2020/03/13/Git/Git常用命令/"},{"title":"Java/BeautifulSoup","date":"2020-03-17T02:48:22.680Z","link":"/2020/03/17/Java/BeautifulSoup/"},{"title":"计算机基础/一门编程语言的学习","date":"2020-03-18T03:12:57.252Z","link":"/2020/03/18/计算机基础/一门编程语言的学习/"},{"title":"学习方法/学习","date":"2020-03-21T08:17:48.502Z","link":"/2020/03/21/学习方法/学习/"},{"title":"Java/SSM","date":"2020-03-23T09:42:08.578Z","link":"/2020/03/23/Java/SSM/"},{"title":"学习方法/学习方法","date":"2020-03-27T06:24:48.844Z","link":"/2020/03/27/学习方法/学习方法/"},{"title":"Grid网页布局","date":"2020-03-27T10:23:45.431Z","link":"/2020/03/27/知识碎片/Grid网页布局/"},{"title":"计算机基础/电脑装机","date":"2020-03-28T04:04:42.482Z","link":"/2020/03/28/计算机基础/电脑装机/"},{"title":"Web/WebLearn/前端浏览器","date":"2020-03-28T16:57:00.238Z","link":"/2020/03/29/Web/WebLearn/前端浏览器/"},{"title":"Web/Basic/HMTL/HTML","date":"2020-03-29T02:55:19.954Z","link":"/2020/03/29/Web/Basic/HMTL/HTML/"},{"title":"静态blog/Markdown/Xmind","date":"2020-03-29T05:46:27.505Z","link":"/2020/03/29/静态blog/Markdown/Xmind/"},{"title":"Web/Basic/CSS/CSS","date":"2020-03-29T11:33:19.914Z","link":"/2020/03/29/Web/Basic/CSS/CSS/"},{"title":"Web/Basic/CSS/CSS3","date":"2020-03-29T11:33:22.681Z","link":"/2020/03/29/Web/Basic/CSS/CSS3/"}],"2020-4":[{"title":"面试/面试题","date":"2020-04-04T14:02:25.157Z","link":"/2020/04/04/面试/面试题/"},{"title":"学习方法/道理","date":"2020-04-06T15:56:41.996Z","link":"/2020/04/06/学习方法/道理/"},{"title":"LeetCode题","date":"2020-04-07T12:03:56.238Z","link":"/2020/04/07/Leetcode/刷LeetCode题/"},{"title":"Web/JavaScript/ES6/ES6报错","date":"2020-04-08T06:44:58.157Z","link":"/2020/04/08/Web/JavaScript/ES6/ES6报错/"},{"title":"学习方法/习惯","date":"2020-04-10T03:48:14.205Z","link":"/2020/04/10/学习方法/习惯/"},{"title":"Web/WebLearn/google插件","date":"2020-04-12T10:58:04.662Z","link":"/2020/04/12/Web/WebLearn/google插件/"},{"title":"静态blog/Markdown/富文本编辑器","date":"2020-04-12T16:26:11.535Z","link":"/2020/04/13/静态blog/Markdown/富文本编辑器/"},{"title":"Web/实例","date":"2020-04-13T09:27:16.263Z","link":"/2020/04/13/Web/实例/"},{"title":"Web/JavaScript/JavaScript/参考手册学习/Browser 对象","date":"2020-04-15T01:47:24.442Z","link":"/2020/04/15/Web/JavaScript/JavaScript/参考手册学习/Browser 对象/"},{"title":"Web/JavaScript/JavaScript/参考手册学习/HTML DOM 对象","date":"2020-04-15T01:47:24.442Z","link":"/2020/04/15/Web/JavaScript/JavaScript/参考手册学习/HTML DOM 对象/"},{"title":"Web/advanced/Regular/正则表达式","date":"2020-04-17T08:29:44.842Z","link":"/2020/04/17/Web/advanced/Regular/正则表达式/"},{"title":"Web/advanced/JSON/JSON","date":"2020-04-17T08:29:44.842Z","link":"/2020/04/17/Web/advanced/JSON/JSON/"},{"title":"Web/advanced/AJAX/AJAX","date":"2020-04-17T08:29:44.842Z","link":"/2020/04/17/Web/advanced/AJAX/AJAX/"}],"2020-5":[{"title":"LInux服务器/linux命令","date":"2020-05-01T13:56:59.880Z","link":"/2020/05/01/LInux服务器/linux命令/"},{"title":"Web/xml","date":"2020-05-02T06:06:27.361Z","link":"/2020/05/02/Web/xml/"},{"title":"Web/iconAnfont/font","date":"2020-05-15T09:11:10.426Z","link":"/2020/05/15/Web/iconAnfont/font/"},{"title":"树莓派/树莓派","date":"2020-05-23T06:58:06.032Z","link":"/2020/05/23/树莓派/树莓派/"},{"title":"Web/Babel 是一个JavaScript 编译器","date":"2020-05-25T17:03:15.288Z","link":"/2020/05/26/Web/Babel 是一个JavaScript 编译器/"}],"2020-6":[{"title":"计算机图形学/计算机图形学","date":"2020-06-07T08:29:12.145Z","link":"/2020/06/07/计算机图形学/计算机图形学/"},{"title":"软件/VScode插件","date":"2020-06-08T08:24:05.312Z","link":"/2020/06/08/软件/VScode插件/"},{"title":"Web/网页效果/滚动视差","date":"2020-06-11T07:17:22.872Z","link":"/2020/06/11/Web/网页效果/滚动视差/"},{"title":"软件/VSCode用法","date":"2020-06-18T17:51:45.432Z","link":"/2020/06/19/软件/VSCode用法/"},{"title":"Hexo学习","date":"2020-06-18T17:52:17.261Z","link":"/2020/06/19/静态blog/Hexo/"},{"title":"软件/Navicat软件的学习","date":"2020-06-24T04:26:05.469Z","link":"/2020/06/24/软件/Navicat软件的学习/"},{"title":"Web/正则表达式案例","date":"2020-06-25T04:56:44.290Z","link":"/2020/06/25/Web/正则表达式案例/"},{"title":"element","date":"2020-06-25T04:56:44.302Z","link":"/2020/06/25/Web/element/"},{"title":"Web/UI框架","date":"2020-06-25T04:56:44.332Z","link":"/2020/06/25/Web/UI框架/"},{"title":"Web/Vue案例","date":"2020-06-25T04:56:44.335Z","link":"/2020/06/25/Web/Vue案例/"},{"title":"Web/vue开发组件库","date":"2020-06-25T04:56:44.349Z","link":"/2020/06/25/Web/vue开发组件库/"},{"title":"Web/Vue商城","date":"2020-06-25T04:56:44.367Z","link":"/2020/06/25/Web/Vue商城/"},{"title":"Web/Xpath教程（2020.2.28）","date":"2020-06-25T04:56:44.371Z","link":"/2020/06/25/Web/Xpath教程（2020.2.28）/"},{"title":"Web/JS实例","date":"2020-06-25T04:56:44.421Z","link":"/2020/06/25/Web/JS实例/"},{"title":"Web/语法错误篇","date":"2020-06-25T04:56:44.425Z","link":"/2020/06/25/Web/语法错误篇/"},{"title":"CSS五种方法元素居中","date":"2020-06-26T07:59:22.095Z","link":"/2020/06/26/知识碎片/CSS五种方法元素居中/"},{"title":"JS的三种事件绑定的方法","date":"2020-06-26T08:04:42.822Z","link":"/2020/06/26/知识碎片/JS的三种事件绑定的方法/"}]}